graphene_django_permissions/__init__.py
graphene_django_permissions/middleware.py
graphene_django_permissions-1.0.0.dist-info/LICENSE
graphene_django_permissions-1.0.0.dist-info/METADATA
graphene_django_permissions-1.0.0.dist-info/WHEEL
graphene_django_permissions-1.0.0.dist-info/RECORD
